usbgen/__init__.py
usbgen/generator.py
usbgen/usb/__init__.py
usbgen/usb/constants.py
usbgen/usb/defaults.py
usbgen/usb/descriptors.py
usbgen/usb/formatters.py
usbgen/usb/cdc/__init__.py
usbgen/usb/cdc/constants.py
usbgen/usb/cdc/descriptors.py
usbgen/usb/video/__init__.py
usbgen/usb/video/constants.py
usbgen/usb/video/descriptors.py
usbgen-0.0.2.dist-info/DESCRIPTION.rst
usbgen-0.0.2.dist-info/METADATA
usbgen-0.0.2.dist-info/RECORD
usbgen-0.0.2.dist-info/WHEEL
usbgen-0.0.2.dist-info/entry_points.txt
usbgen-0.0.2.dist-info/metadata.json
usbgen-0.0.2.dist-info/top_level.txt
