Metadata-Version: 2.0
Name: usbgen
Version: 0.0.2
Summary: Generate usb descriptors for C applications
Home-page: https://github.com/matematik7/usb-descriptor-generator
Author: Domen Ipavec
Author-email: domen@ipavec.net
License: MIT
Keywords: C usb
Platform: UNKNOWN
Classifier: Development Status :: 3 - Alpha
Classifier: License :: OSI Approved :: MIT License
Classifier: Programming Language :: Python :: 2
Classifier: Programming Language :: Python :: 2.6
Classifier: Programming Language :: Python :: 2.7
Classifier: Programming Language :: Python :: 3
Classifier: Programming Language :: Python :: 3.3
Classifier: Programming Language :: Python :: 3.4
Classifier: Programming Language :: Python :: 3.5
Requires-Dist: jinja2
Provides-Extra: dev
Requires-Dist: check-manifest; extra == 'dev'
Provides-Extra: test
Requires-Dist: coverage; extra == 'test'
